source_linkedin_pages/__init__.py
source_linkedin_pages/manifest.yaml
source_linkedin_pages/run.py
source_linkedin_pages/source.py
airbyte_source_linkedin_pages-1.0.17.dist-info/METADATA
airbyte_source_linkedin_pages-1.0.17.dist-info/WHEEL
airbyte_source_linkedin_pages-1.0.17.dist-info/entry_points.txt
airbyte_source_linkedin_pages-1.0.17.dist-info/RECORD
