Metadata-Version: 2.1
Name: airbyte-source-linkedin-pages
Version: 1.0.17
Summary: Source implementation for linkedin-pages.
Home-page: https://airbyte.com
License: MIT
Author: Airbyte
Author-email: contact@airbyte.io
Requires-Python: >=3.9,<3.12
Classifier: License :: OSI Approved :: MIT License
Classifier: Programming Language :: Python :: 3
Classifier: Programming Language :: Python :: 3.9
Classifier: Programming Language :: Python :: 3.10
Classifier: Programming Language :: Python :: 3.11
Requires-Dist: airbyte-cdk (==0.80.0)
Requires-Dist: pendulum (==2.1.2)
Project-URL: Documentation, https://docs.airbyte.com/integrations/sources/linkedin-pages
Project-URL: Repository, https://github.com/airbytehq/airbyte
